README.md
setup.py
bin/hostb_client
hostb_client/__init__.py
hostb_client/utils.py
hostb_client.egg-info/PKG-INFO
hostb_client.egg-info/SOURCES.txt
hostb_client.egg-info/dependency_links.txt
hostb_client.egg-info/requires.txt
hostb_client.egg-info/top_level.txt