Metadata-Version: 2.1
Name: hostb-client
Version: 15
Summary: hostb_client is a command line client for hostb.
Home-page: https://r-w-x.org/r/hostb_client
Author: j
Author-email: j@mailb.org
License: GPLv3
Classifier: Operating System :: OS Independent
Classifier: Programming Language :: Python
Classifier: Programming Language :: Python :: 3
Classifier: License :: OSI Approved :: GNU General Public License (GPL)
